hygiea/__init__.py
hygiea/__version__.py
hygiea/api.py
hygiea/hygiea.py
hygiea/analysis/__init__.py
hygiea/cli/__init__.py
hygiea/cli/main.py
hygiea/core/__init__.py
hygiea/imputation/__init__.py
hygiea/imputation/imputer.py
hygiea/io/__init__.py
hygiea/pipeline/__init__.py
hygiea/preprocessing/__init__.py
hygiea/specialized/__init__.py
tests/__init__.py
hygiea-2.0.0.dist-info/METADATA
hygiea-2.0.0.dist-info/WHEEL
hygiea-2.0.0.dist-info/entry_points.txt
hygiea-2.0.0.dist-info/top_level.txt
hygiea-2.0.0.dist-info/RECORD
